deepset_mcp/__init__.py
deepset_mcp/config.py
deepset_mcp/initialize_embedding_model.py
deepset_mcp/main.py
deepset_mcp/py.typed
deepset_mcp/api/__init__.py
deepset_mcp/api/client.py
deepset_mcp/api/exceptions.py
deepset_mcp/api/protocols.py
deepset_mcp/api/shared_models.py
deepset_mcp/api/transport.py
deepset_mcp/api/custom_components/__init__.py
deepset_mcp/api/custom_components/models.py
deepset_mcp/api/custom_components/protocols.py
deepset_mcp/api/custom_components/resource.py
deepset_mcp/api/haystack_service/__init__.py
deepset_mcp/api/haystack_service/protocols.py
deepset_mcp/api/haystack_service/resource.py
deepset_mcp/api/indexes/__init__.py
deepset_mcp/api/indexes/models.py
deepset_mcp/api/indexes/protocols.py
deepset_mcp/api/indexes/resource.py
deepset_mcp/api/integrations/__init__.py
deepset_mcp/api/integrations/models.py
deepset_mcp/api/integrations/protocols.py
deepset_mcp/api/integrations/resource.py
deepset_mcp/api/pipeline/__init__.py
deepset_mcp/api/pipeline/models.py
deepset_mcp/api/pipeline/protocols.py
deepset_mcp/api/pipeline/resource.py
deepset_mcp/api/pipeline_template/__init__.py
deepset_mcp/api/pipeline_template/models.py
deepset_mcp/api/pipeline_template/protocols.py
deepset_mcp/api/pipeline_template/resource.py
deepset_mcp/api/secrets/__init__.py
deepset_mcp/api/secrets/models.py
deepset_mcp/api/secrets/protocols.py
deepset_mcp/api/secrets/resource.py
deepset_mcp/api/user/__init__.py
deepset_mcp/api/user/protocols.py
deepset_mcp/api/user/resource.py
deepset_mcp/api/workspace/__init__.py
deepset_mcp/api/workspace/models.py
deepset_mcp/api/workspace/protocols.py
deepset_mcp/api/workspace/resource.py
deepset_mcp/mcp/__init__.py
deepset_mcp/mcp/server.py
deepset_mcp/mcp/store.py
deepset_mcp/mcp/tool_factory.py
deepset_mcp/mcp/tool_models.py
deepset_mcp/mcp/tool_registry.py
deepset_mcp/prompts/deepset_copilot_prompt.md
deepset_mcp/prompts/deepset_debugging_agent.md
deepset_mcp/tokonomics/__init__.py
deepset_mcp/tokonomics/decorators.py
deepset_mcp-0.0.11.dist-info/METADATA
deepset_mcp-0.0.11.dist-info/WHEEL
deepset_mcp-0.0.11.dist-info/entry_points.txt
deepset_mcp-0.0.11.dist-info/licenses/LICENSE
deepset_mcp-0.0.11.dist-info/RECORD
