Metadata-Version: 2.4
Name: deepset-mcp
Version: 0.0.11
Summary: Collection of MCP tools and Agents to work with the deepset AI platform. Create, debug or learn about pipelines on the platform. Useable from the CLI, Cursor, Claude Code, or other MCP clients.
Project-URL: Homepage, https://deepset.ai
Author-email: Mathis Lucka <mathis.lucka@deepset.ai>, Tanay Soni <tanay.soni@deepset.ai>
License-Expression: Apache-2.0
License-File: LICENSE
Keywords: Agents,Haystack,LLM,MCP,deepset,pipelines
Classifier: Development Status :: 4 - Beta
Classifier: Intended Audience :: Developers
Classifier: License :: Freely Distributable
Classifier: License :: OSI Approved :: Apache Software License
Classifier: Operating System :: OS Independent
Classifier: Programming Language :: Python
Classifier: Programming Language :: Python :: 3
Classifier: Programming Language :: Python :: 3.11
Classifier: Programming Language :: Python :: 3.12
Classifier: Programming Language :: Python :: 3.13
Classifier: Topic :: Scientific/Engineering :: Artificial Intelligence
Requires-Python: >=3.11
Requires-Dist: fastapi
Requires-Dist: glom
Requires-Dist: httpx
Requires-Dist: mcp>=1.10.1
Requires-Dist: model2vec
Requires-Dist: numpy
Requires-Dist: orjson
Requires-Dist: pydantic>=2.0.0
Requires-Dist: pyjwt[crypto]
Requires-Dist: pyyaml
Requires-Dist: rich
Requires-Dist: typer
Provides-Extra: redis
Requires-Dist: redis>=4.0.0; extra == 'redis'
